{
  "frontmatter": {
    "title": "23216d82"
  },
  "content": {
    "source": {
      "locale": "en-US",
      "hashes": [
        "77da26a5",
        "26122f94",
        "2a7816d0",
        "3c560570",
        "9691800c",
        "7e4068da",
        "c44c1f6b",
        "f2b84a2a",
        "3d77f92",
        "91e6f82e",
        "a312a3f7",
        "d3e03e76",
        "acfcd3ce",
        "d2365e35",
        "af0fce2",
        "92c2140",
        "1f4770e5",
        "146b3afc"
      ]
    },
    "targets": {
      "zh-CN": [
        "77da26a5",
        "26122f94",
        "2a7816d0",
        "3c560570",
        "9691800c",
        "7e4068da",
        "c44c1f6b",
        "f2b84a2a",
        "3d77f92",
        "91e6f82e",
        "a312a3f7",
        "d3e03e76",
        "acfcd3ce",
        "d2365e35",
        "af0fce2",
        "92c2140",
        "1f4770e5",
        "146b3afc"
      ]
    }
  }
}
