{
  "frontmatter": {
    "title": "d7ae8e9e"
  },
  "content": {
    "source": {
      "locale": "en-US",
      "hashes": [
        "77da26a5",
        "f015f69a",
        "c770ec40",
        "9267a3a",
        "15376261",
        "2a7816d0",
        "3dab564a",
        "b62205e7",
        "35bc0a6e",
        "4bb1139c",
        "c697e0a0",
        "1135cb8e",
        "43aae7f3",
        "25fe358b",
        "9413283",
        "ecb7916f",
        "a40917e4",
        "bcdaddfc",
        "8762e9b8",
        "54597c7c",
        "96e9e665",
        "add698fb",
        "43628d33",
        "acc96ff7",
        "1f4770e5",
        "956d9bb9"
      ]
    },
    "targets": {
      "zh-CN": [
        "77da26a5",
        "f015f69a",
        "c770ec40",
        "9267a3a",
        "15376261",
        "2a7816d0",
        "3dab564a",
        "b62205e7",
        "35bc0a6e",
        "4bb1139c",
        "c697e0a0",
        "1135cb8e",
        "43aae7f3",
        "25fe358b",
        "9413283",
        "ecb7916f",
        "a40917e4",
        "bcdaddfc",
        "8762e9b8",
        "54597c7c",
        "96e9e665",
        "add698fb",
        "43628d33",
        "acc96ff7",
        "1f4770e5",
        "956d9bb9"
      ]
    }
  }
}
