{
  "frontmatter": {
    "title": "3597530c"
  },
  "content": {
    "source": {
      "locale": "en-US",
      "hashes": [
        "77da26a5",
        "f2fac493",
        "e59129d",
        "b2998e25",
        "b809df68",
        "2a7816d0",
        "feff2220",
        "545d6966",
        "266557de",
        "ef0b0578",
        "f5228623",
        "53463c08",
        "f875e8b1",
        "5aecda15",
        "4c36d999",
        "fd1a3ce2",
        "6c88082e",
        "2b757c50",
        "3c1db723",
        "545d6966",
        "9227a6a9",
        "b0e6b589",
        "f5228623",
        "a56088d4",
        "9db06f93",
        "290b81c3",
        "ebc9910f",
        "f26ce216",
        "a18d7e96",
        "4b235c5c",
        "1f4770e5",
        "559f3236"
      ]
    },
    "targets": {
      "zh-CN": [
        "77da26a5",
        "f2fac493",
        "e59129d",
        "b2998e25",
        "b809df68",
        "2a7816d0",
        "feff2220",
        "545d6966",
        "266557de",
        "ef0b0578",
        "f5228623",
        "53463c08",
        "f875e8b1",
        "5aecda15",
        "4c36d999",
        "fd1a3ce2",
        "6c88082e",
        "2b757c50",
        "3c1db723",
        "545d6966",
        "9227a6a9",
        "b0e6b589",
        "f5228623",
        "a56088d4",
        "9db06f93",
        "290b81c3",
        "ebc9910f",
        "f26ce216",
        "a18d7e96",
        "4b235c5c",
        "1f4770e5",
        "559f3236"
      ]
    }
  }
}
