{
  "frontmatter": {
    "title": "6eba2a9b"
  },
  "content": {
    "source": {
      "locale": "en-US",
      "hashes": [
        "77da26a5",
        "31974a8d",
        "4a7ee626",
        "2a7816d0",
        "ea5986",
        "a68d98f3",
        "c0348e7d",
        "76160559",
        "99ce9069",
        "73ce0b88",
        "3fbbfd7",
        "88f06e97",
        "57c7cb7d",
        "8b4c4ae9",
        "9ade64f2",
        "ff201ac3",
        "3b467292",
        "1f4770e5",
        "4a6a1cdc"
      ]
    },
    "targets": {
      "zh-CN": [
        "77da26a5",
        "31974a8d",
        "4a7ee626",
        "2a7816d0",
        "ea5986",
        "a68d98f3",
        "c0348e7d",
        "76160559",
        "99ce9069",
        "73ce0b88",
        "3fbbfd7",
        "88f06e97",
        "57c7cb7d",
        "8b4c4ae9",
        "9ade64f2",
        "ff201ac3",
        "3b467292",
        "1f4770e5",
        "4a6a1cdc"
      ]
    }
  }
}
